fade/__init__.py
fade/fallacy_detector.py
fade/transcription_features/live_transcription.py
python_fade-0.0.1.dist-info/LICENSE
python_fade-0.0.1.dist-info/METADATA
python_fade-0.0.1.dist-info/WHEEL
python_fade-0.0.1.dist-info/top_level.txt
python_fade-0.0.1.dist-info/RECORD
