Metadata-Version: 2.1
Name: python-fade
Version: 0.0.1
Summary: FADE is a project aimed at detecting fallacies in various forms of speech. Upgrading and optimizing this tool will enable the identification of unethical, manipulative, and persuasive discourse from politicians, influencers, and even our friends and families.
Author-email: Diogo Pedrosa <diogofranciscop@hotmail.com>, Duarte Gomes <duarte.gcgcomes@gmail.com>
Project-URL: Homepage, https://github.com/AiFlowSolutions/FADE
Project-URL: Issues, https://github.com/AiFlowSolutions/FADE/issues
Classifier: Programming Language :: Python :: 3
Classifier: License :: OSI Approved :: MIT License
Classifier: Operating System :: OS Independent
Requires-Python: >=3.11.7
License-File: LICENSE
Requires-Dist: annotated-types>=0.7.0
Requires-Dist: anyio>=4.4.0
Requires-Dist: beautifulsoup4>=4.12.3
Requires-Dist: cachetools>=5.5.0
Requires-Dist: certifi==2024.7.4
Requires-Dist: charset-normalizer>=3.3.2
Requires-Dist: distro>=1.9.0
Requires-Dist: google>=3.0.0
Requires-Dist: google-api-core>=2.19.2
Requires-Dist: google-auth>=2.34.0
Requires-Dist: google-cloud-speech>=2.27.0
Requires-Dist: googleapis-common-protos>=1.65.0
Requires-Dist: groq>=0.10.0
Requires-Dist: grpcio>=1.66.1
Requires-Dist: grpcio-status>=1.66.1
Requires-Dist: h11>=0.14.0
Requires-Dist: httpcore>=1.0.5
Requires-Dist: httpx>=0.27.2
Requires-Dist: idna>=3.8
Requires-Dist: proto-plus>=1.24.0
Requires-Dist: protobuf>=5.28.0
Requires-Dist: pyasn1>=0.6.0
Requires-Dist: pyasn1-modules>=0.4.0
Requires-Dist: PyAudio>=0.2.14
Requires-Dist: pydantic>=2.8.2
Requires-Dist: pydantic-core>=2.20.1
Requires-Dist: python-dotenv>=1.0.1
Requires-Dist: requests>=2.32.3
Requires-Dist: rsa>=4.9
Requires-Dist: sniffio>=1.3.1
Requires-Dist: soupsieve>=2.6
Requires-Dist: typing-extensions>=4.12.2
Requires-Dist: urllib3>=2.2.2
